data/__init__.py
data/gpu_1_json.py
data/gpu_1_xml.py
data/gpu_4_json.py
data/gpu_4_xml.py
data/nvme_json.py
data/sensors_amd_epyc_json.py
data/sensors_intel_json.py
server_metrics/__init__.py
server_metrics/__main__.py
server_metrics/collectors/__init__.py
server_metrics/collectors/gpu_collector.py
server_metrics/collectors/machine_collector.py
server_metrics/collectors/nvme_collector.py
server_metrics/collectors/sensors_collector.py
server_metrics/utils/__init__.py
server_metrics/utils/configuration.py
server_metrics/utils/conversion.py
server_metrics/utils/execute.py
server_metrics/utils/filter.py
server_metrics/utils/models.py
server_metrics/utils/parse_gpu_json.py
server_metrics/utils/ssh.py
server_metrics/utils/xml_parser.py
server_metrics/utils/prom/__init__.py
server_metrics/utils/prom/gpu.py
server_metrics/utils/prom/machine.py
server_metrics/utils/prom/nvme.py
server_metrics/utils/prom/sensors.py
tests/__init__.py
tests/conftest.py
tests/collectors/__init__.py
tests/collectors/test_gpu_collector.py
tests/utils/__init__.py
tests/utils/test_configuration.py
tests/utils/test_conversion.py
tests/utils/test_filter.py
tests/utils/test_parse_gpu_json.py
tests/utils/test_xml_parser.py
starlyng_server_metrics-0.9.10.dist-info/METADATA
starlyng_server_metrics-0.9.10.dist-info/WHEEL
starlyng_server_metrics-0.9.10.dist-info/entry_points.txt
starlyng_server_metrics-0.9.10.dist-info/top_level.txt
starlyng_server_metrics-0.9.10.dist-info/RECORD
