Metadata-Version: 2.1
Name: starlyng-server-metrics
Version: 0.9.10
Summary: This project gathers metrics for local or hosted servers that can be run on a server used to post data to Grafana and Prometheus.
Home-page: https://github.com/starlyngapp/server-metrics
Author: Justin Sherwood
Author-email: justin@sherwood.fm
License: UNKNOWN
Platform: UNKNOWN
Classifier: Development Status :: 3 - Alpha
Classifier: Intended Audience :: Developers
Classifier: Topic :: Software Development :: Build Tools
Classifier: Programming Language :: Python :: 3
Classifier: Operating System :: OS Independent
Requires-Python: >=3.7
Requires-Dist: python-dotenv
Provides-Extra: dev
Requires-Dist: pytest; extra == "dev"
Requires-Dist: pytest-mock==3.14.0; extra == "dev"
Requires-Dist: pylint==3.2.2; extra == "dev"
Requires-Dist: twine; extra == "dev"
Requires-Dist: wheel; extra == "dev"
